{"text": "2022-10-14T19:11:50.189158+0300, DEBUG, Успешный запуск!\n", "record": {"elapsed": {"repr": "0:00:06.709833", "seconds": 6.709833}, "exception": null, "extra": {}, "file": {"name": "main.py", "path": "/Users/ludmilaromanova/Dev/weather_project/main.py"}, "function": "get_sourse", "level": {"icon": "🐞", "name": "DEBUG", "no": 10}, "line": 27, "message": "Успешный запуск!", "module": "main", "name": "__main__", "process": {"id": 8541, "name": "MainProcess"}, "thread": {"id": 4710364672, "name": "MainThread"}, "time": {"repr": "2022-10-14 19:11:50.189158+03:00", "timestamp": 1665763910.189158}}}
{"text": "2022-10-14T19:12:00.689591+0300, DEBUG, Парсер закончил работу!\n", "record": {"elapsed": {"repr": "0:00:17.210266", "seconds": 17.210266}, "exception": null, "extra": {}, "file": {"name": "main.py", "path": "/Users/ludmilaromanova/Dev/weather_project/main.py"}, "function": "get_sheet_weather", "level": {"icon": "🐞", "name": "DEBUG", "no": 10}, "line": 294, "message": "Парсер закончил работу!", "module": "main", "name": "__main__", "process": {"id": 8541, "name": "MainProcess"}, "thread": {"id": 4710364672, "name": "MainThread"}, "time": {"repr": "2022-10-14 19:12:00.689591+03:00", "timestamp": 1665763920.689591}}}
